stavyagoel_topsis/__init__.py
stavyagoel_topsis/topsis.py
topsis102203640-0.1.1.dist-info/METADATA
topsis102203640-0.1.1.dist-info/WHEEL
topsis102203640-0.1.1.dist-info/top_level.txt
topsis102203640-0.1.1.dist-info/RECORD
