Metadata-Version: 2.1
Name: topsis102203640
Version: 0.1.1
Summary: A basic TOPSIS package for decision analysis.
Home-page: https://github.com/stavyagoel/topsis
Author: stavya
Author-email: your_email@example.com
Classifier: Programming Language :: Python :: 3
Classifier: License :: OSI Approved :: MIT License
Classifier: Operating System :: OS Independent
Requires-Python: >=3.6
Requires-Dist: pandas
Requires-Dist: numpy
